{
  "name": "PrivilegedRole",
  "description": "",
  "collectionOf": null,
  "isComplexType": false,
  "isEntitySet": false,
  "allowPatch": true,
  "allowUpsert": true,
  "allowPatchCreate": true,
  "allowDelete": true,
  "info": null,
  "propertyNotes": "",
  "relationshipNotes": "",
  "methodNotes": "",
  "createDescription": "",
  "updateDescription": "",
  "deleteDescription": "",
  "restPath": [

  ],
  "properties": [
    {
      "name": "Id",
      "description": "",
      "isKey": true,
      "dataType": "Guid",
      "isReadOnly": true,
      "enumName": null,
      "isCollection": false,
      "isRelationship": false,
      "allowPostToCollection": true,
      "isNullable": false,
      "isUnicode": null
    },
    {
      "name": "Name",
      "description": "",
      "isKey": false,
      "dataType": "String",
      "isReadOnly": false,
      "enumName": null,
      "isCollection": false,
      "isRelationship": false,
      "allowPostToCollection": true,
      "isNullable": null,
      "isUnicode": false
    },
    {
      "name": "Summary",
      "description": "",
      "isKey": false,
      "dataType": "PrivilegedRoleSummary",
      "isReadOnly": true,
      "enumName": null,
      "isCollection": false,
      "isRelationship": true,
      "allowPostToCollection": true,
      "isNullable": false,
      "isUnicode": null
    },
    {
      "name": "Settings",
      "description": "",
      "isKey": false,
      "dataType": "PrivilegedRoleSettings",
      "isReadOnly": true,
      "enumName": null,
      "isCollection": false,
      "isRelationship": true,
      "allowPostToCollection": true,
      "isNullable": false,
      "isUnicode": null
    },
    {
      "name": "Assignments",
      "description": "",
      "isKey": false,
      "dataType": "PrivilegedRoleAssignment",
      "isReadOnly": true,
      "enumName": null,
      "isCollection": true,
      "isRelationship": true,
      "allowPostToCollection": true,
      "isNullable": true,
      "isUnicode": null
    }
  ],
  "methods": [
    {
      "name": "SelfActivate",
      "displayName": "",
      "description": "",
      "prerequisites": "",
      "returnType": "PrivilegedRoleAssignment",
      "isReturnNullable": null,
      "isReturnTypeCollection": false,
      "httpSuccessCode": "200",
      "isFunction": false,
      "scopes": [

      ],
      "errorCodes": [

      ],
      "parameters": [
        {
          "name": "Reason",
          "description": "",
          "dataType": "String",
          "isRequired": true,
          "enumName": null,
          "isNullable": null,
          "isUnicode": false
        },
        {
          "name": "Duration",
          "description": "",
          "dataType": "String",
          "isRequired": true,
          "enumName": null,
          "isNullable": null,
          "isUnicode": false
        },
        {
          "name": "TicketNumber",
          "description": "",
          "dataType": "String",
          "isRequired": true,
          "enumName": null,
          "isNullable": null,
          "isUnicode": false
        },
        {
          "name": "TicketSystem",
          "description": "",
          "dataType": "String",
          "isRequired": true,
          "enumName": null,
          "isNullable": null,
          "isUnicode": false
        }
      ]
    },
    {
      "name": "SelfDeactivate",
      "displayName": "",
      "description": "",
      "prerequisites": "",
      "returnType": "PrivilegedRoleAssignment",
      "isReturnNullable": null,
      "isReturnTypeCollection": false,
      "httpSuccessCode": "200",
      "isFunction": false,
      "scopes": [

      ],
      "errorCodes": [

      ],
      "parameters": [

      ]
    }
  ]
}